README.rst
setup.py
redfocus/__init__.py
redfocus.egg-info/PKG-INFO
redfocus.egg-info/SOURCES.txt
redfocus.egg-info/dependency_links.txt
redfocus.egg-info/entry_points.txt
redfocus.egg-info/requires.txt
redfocus.egg-info/top_level.txt