Metadata-Version: 1.0
Name: redfocus
Version: 0.5
Summary: Import Redmine issues into OmniFocus
Home-page: UNKNOWN
Author: Brandon Adams
Author-email: brandon.adams@me.com
License: UNKNOWN
Platform: UNKNOWN
